Metadata-Version: 2.1
Name: tearex
Version: 0.1.1
Summary: A Python SDK for the TeaRex API
Home-page: https://github.com/tearex-ai/tearex-py
Author: ppierzc
Author-email: paul@teacode.io
License: UNKNOWN
Platform: UNKNOWN
Classifier: Programming Language :: Python :: 3
Classifier: License :: OSI Approved :: MIT License
Classifier: Operating System :: OS Independent
Requires-Python: >=3.6
